agilecrm/__init__.py
agilecrm-0.0.3.dist-info/DESCRIPTION.rst
agilecrm-0.0.3.dist-info/METADATA
agilecrm-0.0.3.dist-info/metadata.json
agilecrm-0.0.3.dist-info/RECORD
agilecrm-0.0.3.dist-info/top_level.txt
agilecrm-0.0.3.dist-info/WHEEL
